odoo/addons/stock_split_picking_kit/README.rst
odoo/addons/stock_split_picking_kit/__init__.py
odoo/addons/stock_split_picking_kit/__manifest__.py
odoo/addons/stock_split_picking_kit/i18n/stock_split_picking_kit.pot
odoo/addons/stock_split_picking_kit/readme/CONTRIBUTORS.rst
odoo/addons/stock_split_picking_kit/readme/DESCRIPTION.rst
odoo/addons/stock_split_picking_kit/static/description/icon.png
odoo/addons/stock_split_picking_kit/static/description/index.html
odoo/addons/stock_split_picking_kit/tests/__init__.py
odoo/addons/stock_split_picking_kit/tests/test_stock_split_picking_kit.py
odoo/addons/stock_split_picking_kit/wizards/__init__.py
odoo/addons/stock_split_picking_kit/wizards/stock_split_picking.py
odoo/addons/stock_split_picking_kit/wizards/stock_split_picking.xml
odoo14_addon_stock_split_picking_kit-14.0.1.0.1.dist-info/METADATA
odoo14_addon_stock_split_picking_kit-14.0.1.0.1.dist-info/WHEEL
odoo14_addon_stock_split_picking_kit-14.0.1.0.1.dist-info/top_level.txt
odoo14_addon_stock_split_picking_kit-14.0.1.0.1.dist-info/RECORD
