Metadata-Version: 2.1
Name: odoo14-addon-stock_split_picking_kit
Version: 14.0.1.0.1
Summary: Split a picking by a number of kits.
Home-page: https://github.com/OCA/stock-logistics-workflow
Author: Camptocamp, BCIM, Odoo Community Association (OCA),
Author-email: support@odoo-community.org
License: AGPL-3
Classifier: Programming Language :: Python
Classifier: Framework :: Odoo
Classifier: Framework :: Odoo :: 14.0
Classifier: License :: OSI Approved :: GNU Affero General Public License v3
Requires-Python: >=3.6
Requires-Dist: odoo14-addon-stock-split-picking
Requires-Dist: odoo<14.1dev,>=14.0a
